MANIFEST.in
setup.cfg
setup.py
browseragents/__init__.py
browseragents/core.py
browseragents/useragentdata.py
browseragents.egg-info/PKG-INFO
browseragents.egg-info/SOURCES.txt
browseragents.egg-info/dependency_links.txt
browseragents.egg-info/not-zip-safe
browseragents.egg-info/top_level.txt
tests/__init__.py
tests/test_browser.py
tests/test_os.py