Metadata-Version: 1.1
Name: browseragents
Version: 0.2.0
Summary: Generate a random user agent
Home-page: https://github.com/walidsa3d/browseragents
Author: Walid Saad
Author-email: walid.sa3d@gmail.com
License: MIT
Keywords: useragents browser agent
Platform: UNKNOWN
Classifier: Development Status :: 4 - Beta
Classifier: Environment :: Console
Classifier: Intended Audience :: End Users/Desktop
Classifier: License :: OSI Approved :: MIT License
Classifier: Natural Language :: English
Classifier: Operating System :: OS Independent
Classifier: Programming Language :: Python :: 2
Classifier: Topic :: Utilities
